{
  "stats": {
    "hp": 35,
    "speed": 20,
    "attack": 46,
    "defense": 34,
    "specialAttack": 35,
    "specialDefense": 45
  },
  "typing": [
    "normal"
  ],
  "evYields": {
    "hp": 0,
    "speed": 0,
    "attack": 1,
    "defense": 0,
    "specialAttack": 0,
    "specialDefense": 0
  },
  "catchRate": 255,
  "genderRatio": 0.5,
  "xpInfo": {
    "baseAmount": 43,
    "gainSpeed": "medium_fast"
  },
  "rideInfo": {
    "type": "pokecraft:none"
  },
  "behaviour": {
    "aggression": "timid",
    "baseFriendship": 70,
    "canSwim": true,
    "isSocial": true
  },
  "abilityPool": {
    "hidden": [
      "pokecraft:run_away",
      "pokecraft:keen_eye"
    ],
    "regular": [
      "pokecraft:frisk"
    ]
  },
  "eggInfo": {
    "groups": [
      "field"
    ],
    "steps": 3825
  },
    "boundingBox": {
    "width": 2,
    "height": 3
  },
  "evolutions": [
    {
      "target": {
        "species": "pokecraft:furret"
      },
      "conditions": [
        {
          "type": "pokecraft:requires_properties",
          "properties": [
            {
              "property": "pokecraft:level",
              "comparison": "greater_than",
              "value": "15"
            }
          ]
        }
      ]
    }
  ],
  "movePool": {
    "levelMoves": {},
    "discMoves": [
      "pokecraft:attract",
      "pokecraft:attract",
      "pokecraft:attract",
      "pokecraft:attract",
      "pokecraft:attract",
      "pokecraft:brickbreak",
      "pokecraft:brickbreak",
      "pokecraft:brickbreak",
      "pokecraft:brickbreak",
      "pokecraft:brickbreak",
      "pokecraft:brutalswing",
      "pokecraft:captivate",
      "pokecraft:chargebeam",
      "pokecraft:chargebeam",
      "pokecraft:chargebeam",
      "pokecraft:chargebeam",
      "pokecraft:confide",
      "pokecraft:confide",
      "pokecraft:cut",
      "pokecraft:cut",
      "pokecraft:cut",
      "pokecraft:cut",
      "pokecraft:dig",
      "pokecraft:dig",
      "pokecraft:dig",
      "pokecraft:dig",
      "pokecraft:doubleteam",
      "pokecraft:doubleteam",
      "pokecraft:doubleteam",
      "pokecraft:doubleteam",
      "pokecraft:doubleteam",
      "pokecraft:echoedvoice",
      "pokecraft:echoedvoice",
      "pokecraft:echoedvoice",
      "pokecraft:endure",
      "pokecraft:facade",
      "pokecraft:facade",
      "pokecraft:facade",
      "pokecraft:facade",
      "pokecraft:facade",
      "pokecraft:flamethrower",
      "pokecraft:flamethrower",
      "pokecraft:flamethrower",
      "pokecraft:flamethrower",
      "pokecraft:flamethrower",
      "pokecraft:fling",
      "pokecraft:fling",
      "pokecraft:fling",
      "pokecraft:fling",
      "pokecraft:focuspunch",
      "pokecraft:focuspunch",
      "pokecraft:frustration",
      "pokecraft:frustration",
      "pokecraft:frustration",
      "pokecraft:frustration",
      "pokecraft:frustration",
      "pokecraft:grassknot",
      "pokecraft:grassknot",
      "pokecraft:grassknot",
      "pokecraft:grassknot",
      "pokecraft:hiddenpower",
      "pokecraft:hiddenpower",
      "pokecraft:hiddenpower",
      "pokecraft:hiddenpower",
      "pokecraft:hiddenpower",
      "pokecraft:honeclaws",
      "pokecraft:honeclaws",
      "pokecraft:icebeam",
      "pokecraft:icebeam",
      "pokecraft:icebeam",
      "pokecraft:icebeam",
      "pokecraft:icebeam",
      "pokecraft:irontail",
      "pokecraft:irontail",
      "pokecraft:naturalgift",
      "pokecraft:poweruppunch",
      "pokecraft:protect",
      "pokecraft:protect",
      "pokecraft:protect",
      "pokecraft:protect",
      "pokecraft:protect",
      "pokecraft:raindance",
      "pokecraft:raindance",
      "pokecraft:raindance",
      "pokecraft:raindance",
      "pokecraft:raindance",
      "pokecraft:rest",
      "pokecraft:rest",
      "pokecraft:rest",
      "pokecraft:rest",
      "pokecraft:rest",
      "pokecraft:retaliate",
      "pokecraft:retaliate",
      "pokecraft:return",
      "pokecraft:return",
      "pokecraft:return",
      "pokecraft:return",
      "pokecraft:return",
      "pokecraft:round",
      "pokecraft:round",
      "pokecraft:round",
      "pokecraft:secretpower",
      "pokecraft:secretpower",
      "pokecraft:secretpower",
      "pokecraft:shadowball",
      "pokecraft:shadowball",
      "pokecraft:shadowball",
      "pokecraft:shadowball",
      "pokecraft:shadowball",
      "pokecraft:shadowclaw",
      "pokecraft:shadowclaw",
      "pokecraft:shadowclaw",
      "pokecraft:shadowclaw",
      "pokecraft:shockwave",
      "pokecraft:shockwave",
      "pokecraft:sleeptalk",
      "pokecraft:sleeptalk",
      "pokecraft:sleeptalk",
      "pokecraft:solarbeam",
      "pokecraft:solarbeam",
      "pokecraft:solarbeam",
      "pokecraft:solarbeam",
      "pokecraft:solarbeam",
      "pokecraft:substitute",
      "pokecraft:substitute",
      "pokecraft:substitute",
      "pokecraft:substitute",
      "pokecraft:sunnyday",
      "pokecraft:sunnyday",
      "pokecraft:sunnyday",
      "pokecraft:sunnyday",
      "pokecraft:sunnyday",
      "pokecraft:surf",
      "pokecraft:surf",
      "pokecraft:surf",
      "pokecraft:surf",
      "pokecraft:surf",
      "pokecraft:swagger",
      "pokecraft:swagger",
      "pokecraft:swagger",
      "pokecraft:swagger",
      "pokecraft:thief",
      "pokecraft:thief",
      "pokecraft:thief",
      "pokecraft:thief",
      "pokecraft:thief",
      "pokecraft:thunderbolt",
      "pokecraft:thunderbolt",
      "pokecraft:thunderbolt",
      "pokecraft:thunderbolt",
      "pokecraft:thunderbolt",
      "pokecraft:toxic",
      "pokecraft:toxic",
      "pokecraft:toxic",
      "pokecraft:toxic",
      "pokecraft:toxic",
      "pokecraft:uturn",
      "pokecraft:uturn",
      "pokecraft:uturn",
      "pokecraft:uturn",
      "pokecraft:waterpulse",
      "pokecraft:waterpulse",
      "pokecraft:whirlpool",
      "pokecraft:workup",
      "pokecraft:workup"
    ],
    "eggMoves": [
      "pokecraft:assist",
      "pokecraft:assist",
      "pokecraft:assist",
      "pokecraft:assist",
      "pokecraft:assist",
      "pokecraft:babydolleyes",
      "pokecraft:captivate",
      "pokecraft:captivate",
      "pokecraft:charm",
      "pokecraft:charm",
      "pokecraft:charm",
      "pokecraft:charm",
      "pokecraft:covet",
      "pokecraft:covet",
      "pokecraft:covet",
      "pokecraft:covet",
      "pokecraft:doubleedge",
      "pokecraft:doubleedge",
      "pokecraft:doubleedge",
      "pokecraft:doubleedge",
      "pokecraft:doubleedge",
      "pokecraft:focusenergy",
      "pokecraft:focusenergy",
      "pokecraft:focusenergy",
      "pokecraft:focusenergy",
      "pokecraft:focusenergy",
      "pokecraft:irontail",
      "pokecraft:irontail",
      "pokecraft:irontail",
      "pokecraft:lastresort",
      "pokecraft:lastresort",
      "pokecraft:lastresort",
      "pokecraft:lastresort",
      "pokecraft:naturalgift",
      "pokecraft:naturalgift",
      "pokecraft:naturalgift",
      "pokecraft:pursuit",
      "pokecraft:pursuit",
      "pokecraft:pursuit",
      "pokecraft:pursuit",
      "pokecraft:pursuit",
      "pokecraft:reversal",
      "pokecraft:reversal",
      "pokecraft:reversal",
      "pokecraft:reversal",
      "pokecraft:reversal",
      "pokecraft:slash",
      "pokecraft:slash",
      "pokecraft:slash",
      "pokecraft:slash",
      "pokecraft:slash",
      "pokecraft:substitute",
      "pokecraft:substitute",
      "pokecraft:trick",
      "pokecraft:trick",
      "pokecraft:trick",
      "pokecraft:trick",
      "pokecraft:trick"
    ],
    "npcMoves": {}
  },
  "transforms": {}
}